MANIFEST.in
README.md
build_models.sh
requirements.txt
setup.py
plncpro/__init__.py
plncpro/__main__.py
plncpro/_version.py
plncpro/build.py
plncpro/prediction.py
plncpro/predstoseq.py
plncpro.egg-info/PKG-INFO
plncpro.egg-info/SOURCES.txt
plncpro.egg-info/dependency_links.txt
plncpro.egg-info/entry_points.txt
plncpro.egg-info/requires.txt
plncpro.egg-info/top_level.txt
plncpro/bin/__init__.py
plncpro/bin/blastparse_mt3.py
plncpro/bin/extractfeatures.py
plncpro/bin/ffparse.py
plncpro/bin/generatelabel.py
plncpro/bin/mergefeatures.py
plncpro/bin/rf/__init__.py
plncpro/bin/rf/buildmodel.py
plncpro/bin/rf/predict.py
plncpro/lib/__init__.py
plncpro/lib/framefinder/__init__.py
plncpro/lib/framefinder/framefinder
plncpro/lib/framefinder/framefinder.model
plncpro/scripts/plncpro_format_ff.sh