Metadata-Version: 2.1
Name: plncpro
Version: 1.2.2
Summary: PlncPRO (Plant Long Non-Coding rna Prediction by Random fOrests) is a program to classify coding (mRNAs) and long non-coding transcripts (lncRNAs).
Home-page: https://github.com/urmi-21/PLncPRO
Author: Urminder Singh
Author-email: usingh@iastate.edu
License: UNKNOWN
Platform: UNKNOWN
Classifier: Programming Language :: Python :: 3
Classifier: License :: OSI Approved :: MIT License
Classifier: Operating System :: Unix
Requires-Python: >=3.5
